mongo_orchestration/__init__.py
mongo_orchestration/_version.py
mongo_orchestration/common.py
mongo_orchestration/compat.py
mongo_orchestration/container.py
mongo_orchestration/daemon.py
mongo_orchestration/errors.py
mongo_orchestration/launch.py
mongo_orchestration/process.py
mongo_orchestration/replica_sets.py
mongo_orchestration/server.py
mongo_orchestration/servers.py
mongo_orchestration/sharded_clusters.py
mongo_orchestration/singleton.py
mongo_orchestration/apps/__init__.py
mongo_orchestration/apps/links.py
mongo_orchestration/apps/replica_sets.py
mongo_orchestration/apps/servers.py
mongo_orchestration/apps/sharded_clusters.py
mongo_orchestration/configurations/replica_sets/allengines.json
mongo_orchestration/configurations/replica_sets/arbiter.json
mongo_orchestration/configurations/replica_sets/auth.json
mongo_orchestration/configurations/replica_sets/basic.json
mongo_orchestration/configurations/replica_sets/clean.json
mongo_orchestration/configurations/replica_sets/mmapv1.json
mongo_orchestration/configurations/replica_sets/ssl.json
mongo_orchestration/configurations/replica_sets/ssl_auth.json
mongo_orchestration/configurations/replica_sets/wiredtiger.json
mongo_orchestration/configurations/servers/auth.json
mongo_orchestration/configurations/servers/basic.json
mongo_orchestration/configurations/servers/clean.json
mongo_orchestration/configurations/servers/mmapv1.json
mongo_orchestration/configurations/servers/ssl.json
mongo_orchestration/configurations/servers/ssl_auth.json
mongo_orchestration/configurations/servers/wiredtiger.json
mongo_orchestration/configurations/sharded_clusters/auth.json
mongo_orchestration/configurations/sharded_clusters/basic.json
mongo_orchestration/configurations/sharded_clusters/clean.json
mongo_orchestration/configurations/sharded_clusters/mmapv1.json
mongo_orchestration/configurations/sharded_clusters/ssl.json
mongo_orchestration/configurations/sharded_clusters/ssl_auth.json
mongo_orchestration-0.11.1.dist-info/METADATA
mongo_orchestration-0.11.1.dist-info/WHEEL
mongo_orchestration-0.11.1.dist-info/entry_points.txt
mongo_orchestration-0.11.1.dist-info/licenses/LICENSE
mongo_orchestration-0.11.1.dist-info/RECORD
