Metadata-Version: 2.4
Name: mongo-orchestration
Version: 0.11.1
Summary: Restful service for managing MongoDB servers
Project-URL: Homepage, https://github.com/10gen/mongo-orchestration
Author: The MongoDB Python Team
License: 
License-File: LICENSE
Keywords: mongo,mongo-orchestration,mongodb,rest,testing
Classifier: Development Status :: 4 - Beta
Classifier: Intended Audience :: Developers
Classifier: License :: OSI Approved :: Apache Software License
Classifier: Operating System :: MacOS :: MacOS X
Classifier: Operating System :: Microsoft :: Windows
Classifier: Operating System :: POSIX
Classifier: Programming Language :: Python :: 3
Classifier: Programming Language :: Python :: 3.9
Classifier: Programming Language :: Python :: 3.10
Classifier: Programming Language :: Python :: 3.11
Classifier: Programming Language :: Python :: 3.12
Classifier: Programming Language :: Python :: 3.13
Classifier: Programming Language :: Python :: Implementation :: CPython
Requires-Python: >=3.9
Requires-Dist: bottle>=0.12.7
Requires-Dist: cheroot>=5.11
Requires-Dist: pymongo<5,>=4
Requires-Dist: requests
Provides-Extra: test
Requires-Dist: coverage>=3.5; extra == 'test'
Requires-Dist: pexpect; extra == 'test'
Requires-Dist: pytest; extra == 'test'
